mylib_008/__init__.py
mylib_008-0.1.dist-info/LICENSE.txt
mylib_008-0.1.dist-info/METADATA
mylib_008-0.1.dist-info/WHEEL
mylib_008-0.1.dist-info/top_level.txt
mylib_008-0.1.dist-info/RECORD
